snyk/__init__.py
snyk/__version__.py
snyk/client.py
snyk/errors.py
snyk/managers.py
snyk/models.py
snyk/test_client.py
snyk/test_data/organizations.json
snyk/test_data/projects.json
snyk/test_data/rest_groups.json
snyk/test_data/rest_targets_page1.json
snyk/test_data/rest_targets_page2.json
snyk/test_data/rest_targets_page3.json
snyk/test_data/v3_groups.json
snyk/test_data/v3_targets_page1.json
snyk/test_data/v3_targets_page2.json
snyk/test_data/v3_targets_page3.json
snyk/test_manager.py
snyk/test_models.py
snyk/test_utils.py
snyk/utils.py
pysnyk-0.9.18.dist-info/LICENSE
pysnyk-0.9.18.dist-info/METADATA
pysnyk-0.9.18.dist-info/WHEEL
pysnyk-0.9.18.dist-info/RECORD
