Metadata-Version: 2.1
Name: pysnyk
Version: 0.9.18
Summary: A Python client for the Snyk API
Home-page: https://github.com/snyk-labs/pysnyk
License: MIT
Author: Gareth Rushgrove
Author-email: garethr@snyk.io
Requires-Python: >=3.7,<4.0
Classifier: License :: OSI Approved :: MIT License
Classifier: Programming Language :: Python :: 3
Classifier: Programming Language :: Python :: 3.7
Classifier: Programming Language :: Python :: 3.8
Classifier: Programming Language :: Python :: 3.9
Classifier: Programming Language :: Python :: 3.10
Classifier: Programming Language :: Python :: 3.11
Requires-Dist: deprecation (>=2.1.0,<3.0.0)
Requires-Dist: importlib_metadata (>=4.11.2,<5.0.0)
Requires-Dist: mashumaro (>=3,<4)
Requires-Dist: requests (>=2.27.1,<3.0.0)
Requires-Dist: retry (>=0.9.2,<0.10.0)
Project-URL: Repository, https://github.com/snyk-labs/pysnyk
